setup.py
RedTaban/__init__.py
RedTaban/konsolTaban.py
RedTaban.egg-info/PKG-INFO
RedTaban.egg-info/SOURCES.txt
RedTaban.egg-info/dependency_links.txt
RedTaban.egg-info/not-zip-safe
RedTaban.egg-info/requires.txt
RedTaban.egg-info/top_level.txt