Metadata-Version: 2.1
Name: RedTaban
Version: 0.2
Summary: Redstone Arayüz Teması
Author: HasanSencer
Author-email: sencerrhs17@icloud.com
License: UNKNOWN
Platform: UNKNOWN
Classifier: Framework :: Django
Classifier: Intended Audience :: Developers
Classifier: Intended Audience :: System Administrators
Classifier: Operating System :: OS Independent
Classifier: Topic :: Software Development
